smspool/__init__.py
smspool/client.py
smspool-0.0.4.dist-info/METADATA
smspool-0.0.4.dist-info/WHEEL
smspool-0.0.4.dist-info/licenses/LICENSE
smspool-0.0.4.dist-info/RECORD
