Metadata-Version: 2.1
Name: smspool
Version: 0.0.4
Summary: A small API Wrapper for smspool.net
Project-URL: Homepage, https://github.com/xm0999/smspool
Project-URL: Bug Tracker, https://github.com/xm0999/smspool/issues
Author-email: xm0999 <xo@rith.xyz>
License: MIT License
Classifier: License :: OSI Approved :: MIT License
Classifier: Operating System :: OS Independent
Classifier: Programming Language :: Python :: 3
Requires-Python: >=3.7
